odyssey_momentum/__init__.py
odyssey_momentum/_version.py
odyssey_momentum/api.py
odyssey_momentum/py.typed
odyssey_momentum/bot/__init__.py
odyssey_momentum/bot/assets.py
odyssey_momentum/bot/bot.py
odyssey_momentum/bot/coords.py
odyssey_momentum/bot/py.typed
odyssey_momentum/bot/user.py
odyssey_momentum/bot/world.py
odyssey_momentum/bot/world_object.py
odyssey_momentum/momentum_api_client/__init__.py
odyssey_momentum/momentum_api_client/client.py
odyssey_momentum/momentum_api_client/errors.py
odyssey_momentum/momentum_api_client/py.typed
odyssey_momentum/momentum_api_client/types.py
odyssey_momentum/momentum_api_client/api/__init__.py
odyssey_momentum/momentum_api_client/api/app/__init__.py
odyssey_momentum/momentum_api_client/api/app/get_health.py
odyssey_momentum/momentum_api_client/api/assets2d/__init__.py
odyssey_momentum/momentum_api_client/api/assets2d/get_api_v_4_assets_2_d_asset_2_d_id.py
odyssey_momentum/momentum_api_client/api/assets3d/__init__.py
odyssey_momentum/momentum_api_client/api/assets3d/delete_api_v_4_assets_3_d_asset_3_d_id.py
odyssey_momentum/momentum_api_client/api/assets3d/get_api_v4_assets_3d.py
odyssey_momentum/momentum_api_client/api/assets3d/get_api_v4_assets_3d_options.py
odyssey_momentum/momentum_api_client/api/assets3d/patch_api_v4_assets_3d_object_id_asset3d_id.py
odyssey_momentum/momentum_api_client/api/assets3d/post_api_v4_assets_3d_upload.py
odyssey_momentum/momentum_api_client/api/auth/__init__.py
odyssey_momentum/momentum_api_client/api/auth/delete_api_v4_users_me_remove_wallet.py
odyssey_momentum/momentum_api_client/api/auth/get_api_v4_auth_challenge.py
odyssey_momentum/momentum_api_client/api/auth/post_api_v4_auth_attach_account.py
odyssey_momentum/momentum_api_client/api/auth/post_api_v4_auth_guest_token.py
odyssey_momentum/momentum_api_client/api/auth/post_api_v4_auth_token.py
odyssey_momentum/momentum_api_client/api/chat/__init__.py
odyssey_momentum/momentum_api_client/api/chat/post_api_v_4_streamchat_object_id_join.py
odyssey_momentum-0.0.1a2.dist-info/METADATA
odyssey_momentum-0.0.1a2.dist-info/WHEEL
odyssey_momentum-0.0.1a2.dist-info/licenses/LICENSE.txt
odyssey_momentum-0.0.1a2.dist-info/RECORD
