Metadata-Version: 2.1
Name: odyssey-momentum
Version: 0.0.1a2
Summary: Python client library for the Odyssey Momentum platform.
Project-URL: Documentation, https://github.com/momentum-xyz/python-client#readme
Project-URL: Issues, https://github.com/momentum-xyz/python-client/issues
Project-URL: Source, https://github.com/momentum-xyz/python-client
License-Expression: MIT
License-File: LICENSE.txt
Classifier: Development Status :: 3 - Alpha
Classifier: Programming Language :: Python
Classifier: Programming Language :: Python :: 3.10
Classifier: Programming Language :: Python :: 3.11
Classifier: Programming Language :: Python :: Implementation :: CPython
Requires-Python: >=3.10
Requires-Dist: anyio
Requires-Dist: attr
Requires-Dist: httpcore[http2]<0.17,>=0.16
Requires-Dist: httpx-ws
Requires-Dist: httpx[http2]>=0.23.1
Requires-Dist: mathutils
Requires-Dist: odyssey-posbus-client
Requires-Dist: web3
Requires-Dist: wsproto
